odoo/addons/onchange_helper/README.rst
odoo/addons/onchange_helper/__init__.py
odoo/addons/onchange_helper/__manifest__.py
odoo/addons/onchange_helper/i18n/de.po
odoo/addons/onchange_helper/i18n/es.po
odoo/addons/onchange_helper/i18n/hr.po
odoo/addons/onchange_helper/i18n/sl.po
odoo/addons/onchange_helper/models/__init__.py
odoo/addons/onchange_helper/models/base.py
odoo/addons/onchange_helper/tests/__init__.py
odoo/addons/onchange_helper/tests/test_onchange_helper.py
odoo11_addon_onchange_helper-11.0.1.0.0.dist-info/DESCRIPTION.rst
odoo11_addon_onchange_helper-11.0.1.0.0.dist-info/METADATA
odoo11_addon_onchange_helper-11.0.1.0.0.dist-info/RECORD
odoo11_addon_onchange_helper-11.0.1.0.0.dist-info/WHEEL
odoo11_addon_onchange_helper-11.0.1.0.0.dist-info/metadata.json
odoo11_addon_onchange_helper-11.0.1.0.0.dist-info/top_level.txt
